{
  "entry": {
    "name": "Ruth's Chris Honululu",
    "text": "Whether it's a romantic steak dinner for two, an important business meeting, or a private party, Ruth's Chris Steak House can accommodate your needs. Our Honolulu steakhouse provides guests with a warm, comfortable atmosphere. The restaurant is also handicap accessible.",
    "website": "http://www.ruthschris.com/Steak-House/6504/Honolulu/Oahu",
    "location": {
      "lat": 21.3,
      "lng": -157.861
    },
    "image": {
      "filename": null,
      "content_type": null,
      "data": null,
      "remove": null
    },
    "address": "500 Ala Moana Blvd,\nRestaurant Row,\nHonolulu, HI 96813",
    "last_visit": "2011-01-14",
    "price_range": 3,
    "stars": 4,
    "vegetarian_menu": null,
    "preview_image": {
      "filename": null,
      "content_type": null,
      "data": null,
      "remove": null
    },
    "@version": 1
  }
}